setup.py
blockext_mindstorms_nxt/__init__.py
blockext_mindstorms_nxt/__main__.py
blockext_mindstorms_nxt.egg-info/PKG-INFO
blockext_mindstorms_nxt.egg-info/SOURCES.txt
blockext_mindstorms_nxt.egg-info/dependency_links.txt
blockext_mindstorms_nxt.egg-info/requires.txt
blockext_mindstorms_nxt.egg-info/top_level.txt