Metadata-Version: 1.1
Name: blockext-mindstorms-nxt
Version: 0.2
Summary: Lego Mindstorms NXT extension for Scratch 2.0 and Snap!
Home-page: https://github.com/blockext/mindstorms-nxt
Author: Tim Radvan, Connor Hudson
Author-email: blob8108@gmail.com
License: MIT
Platform: UNKNOWN
Classifier: Programming Language :: Python
